django_partial_page
